myclippings/__init__.py
myclippings/clipping.py
myclippings/main.py
myclippings/parsers.py
myclippings-0.0.6.dist-info/METADATA
myclippings-0.0.6.dist-info/WHEEL
myclippings-0.0.6.dist-info/licenses/LICENSE
myclippings-0.0.6.dist-info/RECORD
