Metadata-Version: 2.1
Name: myclippings
Version: 0.0.6
Summary: Parses My Clippings.txt
Author-email: Belen Buccolo <belenbuccolo@gmail.com>
License-Expression: MIT
License-File: LICENSE
Keywords: amazon,clippings,kindle,kindle-clippings,parser
Classifier: Development Status :: 2 - Pre-Alpha
Classifier: License :: OSI Approved :: MIT License
Classifier: Natural Language :: English
Classifier: Operating System :: OS Independent
Classifier: Programming Language :: Python :: 3.7
Classifier: Topic :: Software Development :: Libraries :: Python Modules
Classifier: Topic :: Utilities
Requires-Python: >=3.7
Requires-Dist: dateparser~=1.2
Requires-Dist: ftfy~=6.1
